{
    "albums": [
        "DAYS of DASH"
    ],
    "commentsnum": 5849,
    "duration": "04:29",
    "hotcomments": [
        {
            "beReplied": [],
            "commentId": 4780545,
            "commentLocationType": 0,
            "content": "樱花庄每一集都有让我看一季的感觉。",
            "decoration": null,
            "expressionUrl": null,
            "liked": false,
            "likedCount": 10860,
            "parentCommentId": 0,
            "pendantData": null,
            "repliedMark": false,
            "showFloorComment": null,
            "status": 0,
            "time": 1412856843276,
            "user": {
                "authStatus": 0,
                "avatarUrl": "https://p2.music.126.net/bTIoFKFaE1-JQpgN3OynGg==/1986817511391283.jpg",
                "expertTags": null,
                "experts": null,
                "liveInfo": null,
                "locationInfo": null,
                "nickname": "帐号已注销",
                "remarkName": null,
                "userId": 38101911,
                "userType": 0,
                "vipRights": null,
                "vipType": 0
            }
        },
        {
            "beReplied": [],
            "commentId": 2595163,
            "commentLocationType": 0,
            "content": "某天成了大人以后。\n如果回想起在樱花庄所度过的时光，会想起什么呢？\n会因为大家都是笨蛋而感叹吗？\n还是会先想起那段热闹又快乐的日子而感到怀念呢？\n如果两者皆是，就没什么好多说的。\n因为，在这里的每一天确实是最棒的。",
            "decoration": null,
            "expressionUrl": null,
            "liked": false,
            "likedCount": 7502,
            "parentCommentId": 0,
            "pendantData": null,
            "repliedMark": false,
            "showFloorComment": null,
            "status": 0,
            "time": 1398856813919,
            "user": {
                "authStatus": 0,
                "avatarUrl": "https://p1.music.126.net/qIRf_RK1cPZrTsndFcJ0-A==/6007731534408021.jpg",
                "expertTags": null,
                "experts": null,
                "liveInfo": null,
                "locationInfo": null,
                "nickname": "Akstsuki",
                "remarkName": null,
                "userId": 9962859,
                "userType": 0,
                "vipRights": null,
                "vipType": 0
            }
        },
        {
            "beReplied": [],
            "commentId": 10020030,
            "commentLocationType": 0,
            "content": "真白x空太  白x空  爱衣x松冈",
            "decoration": null,
            "expressionUrl": null,
            "liked": false,
            "likedCount": 6448,
            "parentCommentId": 0,
            "pendantData": null,
            "repliedMark": false,
            "showFloorComment": null,
            "status": 0,
            "time": 1423012239201,
            "user": {
                "authStatus": 0,
                "avatarUrl": "https://p1.music.126.net/fyB0yrS152al38yIdTNtbA==/6631154627781446.jpg",
                "expertTags": null,
                "experts": null,
                "liveInfo": null,
                "locationInfo": null,
                "nickname": "ir_yuki",
                "remarkName": null,
                "userId": 32813922,
                "userType": 0,
                "vipRights": null,
                "vipType": 0
            }
        },
        {
            "beReplied": [],
            "commentId": 156538384,
            "commentLocationType": 0,
            "content": "每次偷懒的时候 就想起了空太 真白 七海他们不停追逐自己的梦想，义无反顾。自己也就又充满了力量，因为樱花庄 因为樱花庄的每个人，让我考试排名在学校从90多，慢慢攀爬至今到了13名。即将面临中考，我将继续为考上清华附中而努力！",
            "decoration": null,
            "expressionUrl": null,
            "liked": false,
            "likedCount": 6145,
            "parentCommentId": 0,
            "pendantData": {
                "id": 7007,
                "imageUrl": "http://p1.music.126.net/ngsBcIlGz2v7VO_IHbjelA==/109951163313138130.jpg"
            },
            "repliedMark": false,
            "showFloorComment": null,
            "status": 0,
            "time": 1463584478942,
            "user": {
                "authStatus": 0,
                "avatarUrl": "https://p1.music.126.net/ma8NC_MpYqC-dK_L81FWXQ==/109951163250233892.jpg",
                "expertTags": null,
                "experts": null,
                "liveInfo": null,
                "locationInfo": null,
                "nickname": "帐号已注销",
                "remarkName": null,
                "userId": 135889073,
                "userType": 0,
                "vipRights": {
                    "associator": {
                        "rights": true,
                        "vipCode": 100
                    },
                    "musicPackage": null,
                    "redVipAnnualCount": -1
                },
                "vipType": 11
            }
        },
        {
            "beReplied": [],
            "commentId": 131725512,
            "commentLocationType": 0,
            "content": "在樱花庄看到男主就有一种看到自己的感觉，感觉自己是那么的平庸无能，周遭比自己优秀的人朝着光鲜灿烂的未来不遗余力的奔跑，我却停滞不前。对自身厌恶感像暴风雨后的野草般疯狂滋长，我发誓不要再做这个令人发呕我，拼上全部的青春与激情，就算狂奔到半死不活也要抓住心中的梦想！",
            "decoration": null,
            "expressionUrl": null,
            "liked": false,
            "likedCount": 5532,
            "parentCommentId": 0,
            "pendantData": null,
            "repliedMark": false,
            "showFloorComment": null,
            "status": 0,
            "time": 1458445348131,
            "user": {
                "authStatus": 0,
                "avatarUrl": "https://p1.music.126.net/A9QVBtLQDav3NQk6ho-06g==/109951163844966408.jpg",
                "expertTags": null,
                "experts": null,
                "liveInfo": null,
                "locationInfo": null,
                "nickname": "洛冬Lonic",
                "remarkName": null,
                "userId": 86663697,
                "userType": 0,
                "vipRights": {
                    "associator": {
                        "rights": true,
                        "vipCode": 100
                    },
                    "musicPackage": null,
                    "redVipAnnualCount": -1
                },
                "vipType": 11
            }
        },
        {
            "beReplied": [],
            "commentId": 10365095,
            "commentLocationType": 0,
            "content": "七海塞高，完美女友啊[亲亲]",
            "decoration": null,
            "expressionUrl": null,
            "liked": false,
            "likedCount": 2790,
            "parentCommentId": 0,
            "pendantData": null,
            "repliedMark": false,
            "showFloorComment": null,
            "status": 0,
            "time": 1423411287901,
            "user": {
                "authStatus": 0,
                "avatarUrl": "https://p1.music.126.net/eBKoOs3TB2T55_qs2Waemw==/18679603046972541.jpg",
                "expertTags": null,
                "experts": null,
                "liveInfo": null,
                "locationInfo": null,
                "nickname": "Ippanshain",
                "remarkName": null,
                "userId": 3752485,
                "userType": 0,
                "vipRights": {
                    "associator": null,
                    "musicPackage": {
                        "rights": true,
                        "vipCode": 220
                    },
                    "redVipAnnualCount": -1
                },
                "vipType": 10
            }
        },
        {
            "beReplied": [],
            "commentId": 7182036,
            "commentLocationType": 0,
            "content": "椎名真白，世界第一呆萌女，[大哭][大哭]",
            "decoration": null,
            "expressionUrl": null,
            "liked": false,
            "likedCount": 2724,
            "parentCommentId": 0,
            "pendantData": null,
            "repliedMark": false,
            "showFloorComment": null,
            "status": 0,
            "time": 1418691648265,
            "user": {
                "authStatus": 0,
                "avatarUrl": "https://p1.music.126.net/LNjyRnjYoV1MeVs6rxzIew==/2539871860811090.jpg",
                "expertTags": null,
                "experts": null,
                "liveInfo": null,
                "locationInfo": null,
                "nickname": "Rain_Layd",
                "remarkName": null,
                "userId": 38488506,
                "userType": 0,
                "vipRights": null,
                "vipType": 0
            }
        },
        {
            "beReplied": [],
            "commentId": 10290114,
            "commentLocationType": 0,
            "content": "真的被动漫中的情节感动过。。那纯真的初恋。。",
            "decoration": null,
            "expressionUrl": null,
            "liked": false,
            "likedCount": 1955,
            "parentCommentId": 0,
            "pendantData": null,
            "repliedMark": false,
            "showFloorComment": null,
            "status": 0,
            "time": 1423320005040,
            "user": {
                "authStatus": 0,
                "avatarUrl": "https://p1.music.126.net/kYNA_wMdYajvWcurOBG0FQ==/19031446765626347.jpg",
                "expertTags": null,
                "experts": null,
                "liveInfo": null,
                "locationInfo": null,
                "nickname": "奏音",
                "remarkName": null,
                "userId": 33454793,
                "userType": 0,
                "vipRights": null,
                "vipType": 0
            }
        },
        {
            "beReplied": [],
            "commentId": 6208849,
            "commentLocationType": 0,
            "content": "樱花庄两首ED都很上乘，尤其是这首。可惜动画最后做烂了…",
            "decoration": null,
            "expressionUrl": null,
            "liked": false,
            "likedCount": 1255,
            "parentCommentId": 0,
            "pendantData": null,
            "repliedMark": false,
            "showFloorComment": null,
            "status": 0,
            "time": 1416805891806,
            "user": {
                "authStatus": 0,
                "avatarUrl": "https://p1.music.126.net/EFviUfOvnAuS3NOT5exDxQ==/3422779699770270.jpg",
                "expertTags": null,
                "experts": null,
                "liveInfo": null,
                "locationInfo": null,
                "nickname": "Paradigm34",
                "remarkName": null,
                "userId": 37458428,
                "userType": 0,
                "vipRights": null,
                "vipType": 0
            }
        },
        {
            "beReplied": [],
            "commentId": 171303239,
            "commentLocationType": 0,
            "content": "明明人气不低、第一季销量却暴死…小说中空太和真白分开又再见于樱花庄的樱花树下、简直不能太感动、友情爱情，现实和梦想都在这部作品里完美诠释，今生不悔爱真白、来世愿入樱花庄！",
            "decoration": null,
            "expressionUrl": null,
            "liked": false,
            "likedCount": 1245,
            "parentCommentId": 0,
            "pendantData": null,
            "repliedMark": false,
            "showFloorComment": null,
            "status": 0,
            "time": 1466350400038,
            "user": {
                "authStatus": 0,
                "avatarUrl": "https://p1.music.126.net/d8kNS9x1rP5PNRgFVeh2Xw==/109951163444807119.jpg",
                "expertTags": null,
                "experts": null,
                "liveInfo": null,
                "locationInfo": null,
                "nickname": "Cowlick_",
                "remarkName": null,
                "userId": 246607259,
                "userType": 0,
                "vipRights": null,
                "vipType": 0
            }
        },
        {
            "beReplied": [
                {
                    "beRepliedCommentId": 3973053,
                    "content": "不喜欢真白，支持七海！",
                    "expressionUrl": null,
                    "status": 0,
                    "user": {
                        "authStatus": 0,
                        "avatarUrl": "https://p1.music.126.net/dPVzUtXz8RxH_ORPWdZLwA==/109951164134235120.jpg",
                        "expertTags": null,
                        "experts": null,
                        "liveInfo": null,
                        "locationInfo": null,
                        "nickname": "Hatsune_凌瑶--香港场见初音啦",
                        "remarkName": null,
                        "userId": 15245751,
                        "userType": 0,
                        "vipRights": null,
                        "vipType": 0
                    }
                }
            ],
            "commentId": 6282021,
            "commentLocationType": 0,
            "content": "真白才是王道[大哭][大哭]",
            "decoration": null,
            "expressionUrl": null,
            "liked": false,
            "likedCount": 1217,
            "parentCommentId": 0,
            "pendantData": null,
            "repliedMark": false,
            "showFloorComment": null,
            "status": 0,
            "time": 1416900822382,
            "user": {
                "authStatus": 0,
                "avatarUrl": "https://p1.music.126.net/dm2utdThsIKX2Ew51aYG3A==/7746059417838255.jpg",
                "expertTags": null,
                "experts": null,
                "liveInfo": null,
                "locationInfo": null,
                "nickname": "奔跑的狗骑兔子",
                "remarkName": null,
                "userId": 30399688,
                "userType": 0,
                "vipRights": {
                    "associator": {
                        "rights": true,
                        "vipCode": 100
                    },
                    "musicPackage": null,
                    "redVipAnnualCount": 1
                },
                "vipType": 11
            }
        },
        {
            "beReplied": [],
            "commentId": 25111568,
            "commentLocationType": 0,
            "content": "龙之介才是真爱",
            "decoration": null,
            "expressionUrl": null,
            "liked": false,
            "likedCount": 1032,
            "parentCommentId": 0,
            "pendantData": null,
            "repliedMark": false,
            "showFloorComment": null,
            "status": 0,
            "time": 1436103845036,
            "user": {
                "authStatus": 0,
                "avatarUrl": "https://p1.music.126.net/Dr-AtjBBor6doHNIK5kL0Q==/1373290037064532.jpg",
                "expertTags": null,
                "experts": null,
                "liveInfo": null,
                "locationInfo": null,
                "nickname": "思兼_",
                "remarkName": null,
                "userId": 74493206,
                "userType": 0,
                "vipRights": {
                    "associator": null,
                    "musicPackage": {
                        "rights": true,
                        "vipCode": 220
                    },
                    "redVipAnnualCount": -1
                },
                "vipType": 10
            }
        },
        {
            "beReplied": [],
            "commentId": 199514720,
            "commentLocationType": 0,
            "content": "中考是樱花庄退的宅，为自己不争气默默抽噎了一晚。现在，已经高三了，樱花庄还在那里，曾无奈悲伤崩溃放弃过，但是，番中那些仿佛身边的角色给了我一次又一次前进的理由。——没有努力，只有拼命！努力是你跑到终点还能大口喘气擦汗，拼命则是终点之后就是医院，玛德，拼了！",
            "decoration": null,
            "expressionUrl": null,
            "liked": false,
            "likedCount": 1001,
            "parentCommentId": 0,
            "pendantData": null,
            "repliedMark": false,
            "showFloorComment": null,
            "status": 0,
            "time": 1471261448640,
            "user": {
                "authStatus": 0,
                "avatarUrl": "https://p1.music.126.net/jYmnkf_L8xcu4pkAuktZAQ==/109951163750578779.jpg",
                "expertTags": null,
                "experts": null,
                "liveInfo": null,
                "locationInfo": null,
                "nickname": "夏言言",
                "remarkName": null,
                "userId": 286289955,
                "userType": 0,
                "vipRights": {
                    "associator": null,
                    "musicPackage": {
                        "rights": true,
                        "vipCode": 220
                    },
                    "redVipAnnualCount": -1
                },
                "vipType": 10
            }
        },
        {
            "beReplied": [],
            "commentId": 133914038,
            "commentLocationType": 0,
            "content": "已经不记得第几周目了，今天又看完了，樱花庄是我现在内心的理想乡啊，不知道未来如何，但是至少我现在是真心喜欢樱花庄，那里的生活比我现在枯燥无味的上学好太多了，就算一个宿舍的人也没有像樱花庄那样玩得来的，真的好喜欢樱花庄的大家",
            "decoration": null,
            "expressionUrl": null,
            "liked": false,
            "likedCount": 714,
            "parentCommentId": 0,
            "pendantData": null,
            "repliedMark": false,
            "showFloorComment": null,
            "status": 0,
            "time": 1458884591987,
            "user": {
                "authStatus": 0,
                "avatarUrl": "https://p1.music.126.net/WVPAiMgUBifGMfZIv-EQkQ==/3265549610729689.jpg",
                "expertTags": null,
                "experts": null,
                "liveInfo": null,
                "locationInfo": null,
                "nickname": "爱莉丝玛格特罗依德",
                "remarkName": null,
                "userId": 51980245,
                "userType": 0,
                "vipRights": null,
                "vipType": 0
            }
        },
        {
            "beReplied": [],
            "commentId": 317206582,
            "commentLocationType": 0,
            "content": "给各位樱花庄舍友:各位，我又回来了。很遗憾之前夸下的海口如今没能实现。这半年的名校生活让我知道了现实的残酷以及天才的真正的意义，也许你只看到了他们玩的时候，殊不知他们背后忘我学习的时间。虽然前30对我尚很遥远，但是我认为我可以做到，他们虽然能忘我学习，但我可以玩命奋斗。",
            "decoration": null,
            "expressionUrl": null,
            "liked": false,
            "likedCount": 512,
            "parentCommentId": 0,
            "pendantData": {
                "id": 7007,
                "imageUrl": "http://p1.music.126.net/ngsBcIlGz2v7VO_IHbjelA==/109951163313138130.jpg"
            },
            "repliedMark": false,
            "showFloorComment": null,
            "status": 0,
            "time": 1487954236259,
            "user": {
                "authStatus": 0,
                "avatarUrl": "https://p1.music.126.net/ma8NC_MpYqC-dK_L81FWXQ==/109951163250233892.jpg",
                "expertTags": null,
                "experts": null,
                "liveInfo": null,
                "locationInfo": null,
                "nickname": "帐号已注销",
                "remarkName": null,
                "userId": 135889073,
                "userType": 0,
                "vipRights": {
                    "associator": {
                        "rights": true,
                        "vipCode": 100
                    },
                    "musicPackage": null,
                    "redVipAnnualCount": -1
                },
                "vipType": 11
            }
        }
    ],
    "musicName": "DAYS of DASH",
    "musicUrl": "http://music.163.com/song/media/outer/url?id=28190728.mp3",
    "music_url": "https://music.163.com/song?id=28190728",
    "singers": [
        "鈴木このみ"
    ]
}