{
    "albums": [
        "お后がよろしくって・・・よ!"
    ],
    "commentsnum": 648,
    "duration": "05:16",
    "hotcomments": [
        {
            "beReplied": [
                {
                    "beRepliedCommentId": 27665972,
                    "content": "我是借着良心字幕组的注释全部看懂了，不过还是觉得这些笑点好冷.....",
                    "expressionUrl": null,
                    "status": 0,
                    "user": {
                        "authStatus": 0,
                        "avatarUrl": "https://p1.music.126.net/5DC4T9wNpiqzDX9_Hy2HWw==/528865124072451.jpg",
                        "expertTags": null,
                        "experts": null,
                        "liveInfo": null,
                        "locationInfo": null,
                        "nickname": "竹中半兵卫重治",
                        "remarkName": null,
                        "userId": 42171663,
                        "userType": 0,
                        "vipRights": null,
                        "vipType": 0
                    }
                }
            ],
            "commentId": 27685121,
            "commentLocationType": 0,
            "content": "两国文化虽然有点相近，交流也很多 但是还是差别很大的....再具体到俗语传说典故什么的就更不一样了 ....没办法.",
            "decoration": null,
            "expressionUrl": null,
            "liked": false,
            "likedCount": 219,
            "parentCommentId": 0,
            "pendantData": null,
            "repliedMark": false,
            "showFloorComment": null,
            "status": 0,
            "time": 1437638729334,
            "user": {
                "authStatus": 0,
                "avatarUrl": "https://p1.music.126.net/9GtGShuKbvC5TXoL1f4dGQ==/7934075907294653.jpg",
                "expertTags": null,
                "experts": null,
                "liveInfo": null,
                "locationInfo": null,
                "nickname": "士官长的忧郁",
                "remarkName": null,
                "userId": 67492451,
                "userType": 0,
                "vipRights": null,
                "vipType": 0
            }
        },
        {
            "beReplied": [],
            "commentId": 129084960,
            "commentLocationType": 0,
            "content": "谁是看了超电磁炮的剪辑来的 举个手",
            "decoration": null,
            "expressionUrl": null,
            "liked": false,
            "likedCount": 127,
            "parentCommentId": 0,
            "pendantData": null,
            "repliedMark": false,
            "showFloorComment": null,
            "status": 0,
            "time": 1457857555813,
            "user": {
                "authStatus": 0,
                "avatarUrl": "https://p1.music.126.net/ozhvI9QEwEXYeoyvzKvHHQ==/3301833423299169.jpg",
                "expertTags": null,
                "experts": null,
                "liveInfo": null,
                "locationInfo": null,
                "nickname": "Hibikom",
                "remarkName": null,
                "userId": 96243677,
                "userType": 0,
                "vipRights": {
                    "associator": {
                        "rights": true,
                        "vipCode": 100
                    },
                    "musicPackage": null,
                    "redVipAnnualCount": -1
                },
                "vipType": 11
            }
        },
        {
            "beReplied": [],
            "commentId": 25791437,
            "commentLocationType": 0,
            "content": "我喜欢手寅！",
            "decoration": null,
            "expressionUrl": null,
            "liked": false,
            "likedCount": 97,
            "parentCommentId": 0,
            "pendantData": null,
            "repliedMark": false,
            "showFloorComment": null,
            "status": 0,
            "time": 1436506627809,
            "user": {
                "authStatus": 0,
                "avatarUrl": "https://p1.music.126.net/qcHqDn3QB6KnubyQ9AYa-Q==/7951668094204753.jpg",
                "expertTags": null,
                "experts": null,
                "liveInfo": null,
                "locationInfo": null,
                "nickname": "gan7",
                "remarkName": null,
                "userId": 12145974,
                "userType": 0,
                "vipRights": null,
                "vipType": 0
            }
        },
        {
            "beReplied": [],
            "commentId": 30841342,
            "commentLocationType": 0,
            "content": "好想看看魔威理的蒙古斑[色]",
            "decoration": null,
            "expressionUrl": null,
            "liked": false,
            "likedCount": 78,
            "parentCommentId": 0,
            "pendantData": null,
            "repliedMark": false,
            "showFloorComment": null,
            "status": 0,
            "time": 1439396026076,
            "user": {
                "authStatus": 0,
                "avatarUrl": "https://p1.music.126.net/LGdR44XhatG862qgovGpXg==/3357908511501317.jpg",
                "expertTags": null,
                "experts": null,
                "liveInfo": null,
                "locationInfo": null,
                "nickname": "Daisy_MBL_sox",
                "remarkName": null,
                "userId": 85423723,
                "userType": 0,
                "vipRights": null,
                "vipType": 0
            }
        },
        {
            "beReplied": [],
            "commentId": 13599735,
            "commentLocationType": 0,
            "content": "仁太！仁太！翔！",
            "decoration": null,
            "expressionUrl": null,
            "liked": false,
            "likedCount": 62,
            "parentCommentId": 0,
            "pendantData": null,
            "repliedMark": false,
            "showFloorComment": null,
            "status": 0,
            "time": 1427429986444,
            "user": {
                "authStatus": 0,
                "avatarUrl": "https://p1.music.126.net/f_LTRI2Wl037BLpvPG-SoA==/7711974557333241.jpg",
                "expertTags": null,
                "experts": null,
                "liveInfo": null,
                "locationInfo": null,
                "nickname": "天月FANG",
                "remarkName": null,
                "userId": 51300646,
                "userType": 0,
                "vipRights": null,
                "vipType": 0
            }
        },
        {
            "beReplied": [],
            "commentId": 1357294698,
            "commentLocationType": 0,
            "content": "落语很像我们的单口相声，处境和我们的相声极为相似，平成年轻一代不喜欢看，很多梗都是江户时期甚至更早的东西，有人说看不懂太正常不过，日本人自己都未必能看懂，一直是靠着日本文化部门的扶持才勉强活着，国内的传统相声也是要有点社会阅历才能听得懂，对于这些半消亡状态的传统技艺，只能一声叹息",
            "decoration": {},
            "expressionUrl": null,
            "liked": false,
            "likedCount": 28,
            "parentCommentId": 0,
            "pendantData": null,
            "repliedMark": false,
            "showFloorComment": null,
            "status": 0,
            "time": 1547449689146,
            "user": {
                "authStatus": 0,
                "avatarUrl": "https://p1.music.126.net/VnZiScyynLG7atLIZ2YPkw==/18686200114669622.jpg",
                "expertTags": null,
                "experts": null,
                "liveInfo": null,
                "locationInfo": null,
                "nickname": "月光疾风步",
                "remarkName": null,
                "userId": 442084360,
                "userType": 0,
                "vipRights": null,
                "vipType": 0
            }
        }
    ],
    "musicName": "お后がよろしくって・・・よ!",
    "musicUrl": "http://music.163.com/song/media/outer/url?id=806013.mp3",
    "music_url": "https://music.163.com/song?id=806013",
    "singers": [
        "佐倉綾音",
        "小岩井ことり",
        "山本希望",
        "南條愛乃",
        "後藤沙緒里"
    ]
}